noodleswrapper/__init__.py
noodleswrapper/noodle.py
noodleswrapper-0.2.dist-info/LICENSE
noodleswrapper-0.2.dist-info/METADATA
noodleswrapper-0.2.dist-info/WHEEL
noodleswrapper-0.2.dist-info/top_level.txt
noodleswrapper-0.2.dist-info/RECORD
