Metadata-Version: 2.1
Name: noodleswrapper
Version: 0.2
Summary: A wrapper used for meme generating using Discord API
Home-page: https://www.frenchnoodles.xyz/api
Author: Kabir Ghai
Author-email: tblackwell1876@gmail.com
License: UNKNOWN
Platform: UNKNOWN
Classifier: Development Status :: 4 - Beta
Classifier: Intended Audience :: Developers
Classifier: License :: OSI Approved :: MIT License
Classifier: Natural Language :: English
Classifier: Operating System :: OS Independent
Classifier: Programming Language :: Python
Requires-Python: >=3.8
Requires-Dist: Discord.py (>=1.7)
